python_package_12175/__init__.py
python_package_12175/calculation.py
python_package_12175-0.0.1.dist-info/METADATA
python_package_12175-0.0.1.dist-info/WHEEL
python_package_12175-0.0.1.dist-info/top_level.txt
python_package_12175-0.0.1.dist-info/RECORD
